capablanca/__init__.py
capablanca/algorithm.py
capablanca/app.py
capablanca/applogger.py
capablanca/batch.py
capablanca/chordal.py
capablanca/parser.py
capablanca/test.py
capablanca/utils.py
capablanca-3.3.dist-info/licenses/LICENSE
capablanca-3.3.dist-info/METADATA
capablanca-3.3.dist-info/WHEEL
capablanca-3.3.dist-info/entry_points.txt
capablanca-3.3.dist-info/top_level.txt
capablanca-3.3.dist-info/RECORD
