Metadata-Version: 2.4
Name: capablanca
Version: 3.3
Summary: Find a 2-Approximate Dominating Set for undirected graph encoded in DIMACS format.
Home-page: https://github.com/frankvegadelgado/capablanca
Author: Frank Vega
Author-email: vega.frank@gmail.com
License: MIT License
Project-URL: Source Code, https://github.com/frankvegadelgado/capablanca
Project-URL: Documentation Research, https://dev.to/frank_vega_987689489099bf/a-2-approximation-algorithm-for-dominating-sets-1aga
Classifier: Topic :: Scientific/Engineering
Classifier: Topic :: Software Development
Classifier: Development Status :: 5 - Production/Stable
Classifier: License :: OSI Approved :: MIT License
Classifier: Programming Language :: Python :: 3.10
Classifier: Environment :: Console
Classifier: Intended Audience :: Developers
Classifier: Intended Audience :: Education
Classifier: Intended Audience :: Information Technology
Classifier: Intended Audience :: Science/Research
Classifier: Natural Language :: English
Requires-Python: >=3.10
License-File: LICENSE
Requires-Dist: numpy>=2.2.1
Requires-Dist: scipy>=1.15.0
Requires-Dist: networkx[default]>=3.4.2
Dynamic: author
Dynamic: author-email
Dynamic: classifier
Dynamic: description
Dynamic: description-content-type
Dynamic: home-page
Dynamic: license
Dynamic: license-file
Dynamic: project-url
Dynamic: requires-dist
Dynamic: requires-python
Dynamic: summary
